{
  "operationName": "Teoría Cuántica",
  "dayCount": 45753,
  "dateline": "DÍA 45753 — MARZO 2026 — REPORTE DE SITUACIÓN",
  "heroHeadline": "Física Cuántica: De la Revolución Teórica a la Carrera por la Computación Cuántica",
  "heroSubtitle": "Seguimiento de más de 125 años de mecánica cuántica: desde Planck y Einstein hasta las computadoras cuánticas de Google, IBM y China, y la carrera por la supremacía cuántica.",
  "footerNote": "Datos compilados de publicaciones científicas, Nobel Foundation, y reportes de la industria cuántica. Todas las cifras están actualizadas a la fecha indicada.",
  "lastUpdated": "2026-03-20T00:00:00Z"
}
