[
  {
    "id": "russia-cuba-oil-tanker-us-blockade-2026-03-30",
    "year": "2026",
    "title": "Russia Sends Oil Tanker to Cuba; OFAC Extends Blockade to Russian-Origin Oil",
    "type": "diplomatic",
    "active": true,
    "detail": "A Russian tanker carrying approximately 100,000 tonnes of crude oil arrived in Havana on March 30, 2026, as Russia attempted to circumvent the US oil blockade imposed by Executive Order 14380. The US Treasury's Office of Foreign Assets Control (OFAC) immediately announced that Cuba's purchases of Russian-origin oil would also be blocked, extending the energy blockade beyond Western suppliers. Al Jazeera reported Russia was preparing a second tanker shipment for early April 2026. Cuba's President Díaz-Canel had publicly acknowledged ongoing diplomatic talks with the US on March 13, with Cuba entering negotiations under duress as fuel shortages affected transportation, food distribution, and utilities across the island. The standoff represented the most acute US-Cuba confrontation since the 1962 Cuban Missile Crisis and underscored the geopolitical dimension of the Trump administration's Latin American policy.",
    "sources": [
      {
        "name": "Al Jazeera: Russia Sending Second Ship with Oil to Cuba Amid US Blockade",
        "tier": 2,
        "url": "https://www.aljazeera.com/news/2026/4/2/russia-sending-second-ship-with-oil-to-cuba-amid-us-blockade",
        "pole": "international"
      },
      {
        "name": "Democracy Now: Cuba Oil Blockade — Negotiations Analysis",
        "tier": 3,
        "url": "https://www.democracynow.org/2026/3/31/cuba_oil_blockade_leogrande_fernandez_negotiations",
        "pole": "western"
      },
      {
        "name": "CNBC: Cuba Crisis — Fuel Tankers, Russia Oil, US Trump",
        "tier": 2,
        "url": "https://www.cnbc.com/2026/03/20/cuba-crisis-fuel-tankers-russia-oil-gas-energy-us-trump.html",
        "pole": "western"
      }
    ],
    "media": [
      {
        "type": "article",
        "url": "https://www.aljazeera.com/news/2026/4/2/russia-sending-second-ship-with-oil-to-cuba-amid-us-blockade",
        "caption": "Russia sends oil tanker to Cuba as the US blockade restricts fuel supplies to the island",
        "source": "Al Jazeera",
        "thumbnail": "https://www.aljazeera.com/news/2026/4/2/russia-sending-second-ship-with-oil-to-cuba-amid-us-blockade"
      }
    ],
    "confidence": "high",
    "eventConfidence": "verified",
    "lastUpdated": "2026-04-19T14:18:37Z"
  }
]
