{
  "lastRun": "2026-04-25T15:03:32.000Z",
  "tracker": "uap-disclosure",
  "sections": {
    "kpis": {
      "lastRun": "2026-04-25T15:03:32.000Z",
      "status": "updated"
    },
    "meta": {
      "lastRun": "2026-04-25T15:03:32.000Z",
      "status": "updated"
    },
    "timeline": {
      "lastRun": "2026-04-25T15:03:32.000Z",
      "status": "updated"
    },
    "claims": {
      "lastRun": "2026-04-25T15:03:32.000Z",
      "status": "updated"
    },
    "political": {
      "lastRun": "2026-04-25T15:03:32.000Z",
      "status": "updated"
    },
    "map": {
      "lastRun": "2026-04-25T15:03:32.000Z",
      "status": "updated"
    },
    "events": {
      "lastRun": "2026-04-25T15:03:32.000Z",
      "status": "updated"
    }
  },
  "consecutiveQuietRuns": 0
}
