{
  "operationName": "World War II",
  "dayCount": 2193,
  "dateline": "Europe / Pacific — September 1, 1939–September 2, 1945",
  "heroHeadline": "World War II: The Deadliest Conflict in Human History",
  "heroSubtitle": "From the Nazi invasion of Poland to atomic bombs over Japan — 6 years of global war, the Holocaust, and the dawn of the nuclear age",
  "footerNote": "Data sourced from NARA, Imperial War Museum, Yad Vashem, US Holocaust Memorial Museum, Russian State Military Archive, and national archives. Casualty figures are estimates; exact totals remain contested.",
  "lastUpdated": "2026-03-20T00:00:00Z"
}
