{
  "operationName": "Conflicto México-EE.UU.",
  "dayCount": 4506,
  "dateline": "DÍA 4506 — MARZO 2026 — REPORTE DE SITUACIÓN",
  "heroHeadline": "México vs EE.UU.: De la Anexión de Texas a la Guerra de los Aranceles",
  "heroSubtitle": "Seguimiento de la relación conflictiva entre México y Estados Unidos: desde la guerra de 1846–48, la pérdida de la mitad del territorio, hasta las tensiones comerciales y migratorias del siglo XXI.",
  "footerNote": "Datos compilados de fuentes históricas, Archivo General de la Nación, y estudios académicos. Todas las cifras estimadas están marcadas.",
  "lastUpdated": "2026-03-20T00:00:00Z"
}
