{
  "lastRun": "2026-04-25T00:00:00.000Z",
  "tracker": "russia",
  "runType": "seed",
  "status": "success",
  "sectionsUpdated": [
    "kpis",
    "timeline",
    "mapPoints",
    "claims",
    "political",
    "econ",
    "casualties",
    "meta"
  ],
  "itemCounts": {
    "kpis": 8,
    "timeline": 9,
    "mapPoints": 30,
    "claims": 20,
    "political": 20,
    "casualties": 10,
    "econ": 10
  },
  "sections": {
    "kpis": { "status": "ok", "count": 8 },
    "timeline": { "status": "ok", "count": 9 },
    "mapPoints": { "status": "ok", "count": 30 },
    "claims": { "status": "ok", "count": 20 },
    "political": { "status": "ok", "count": 20 },
    "casualties": { "status": "ok", "count": 10 },
    "econ": { "status": "ok", "count": 10 }
  }
}
