{
  "lastRun": "2026-04-18T14:05:23Z",
  "tracker": "united-states",
  "sections": {
    "events": {
      "lastRun": "2026-04-18T14:05:23Z",
      "status": "updated"
    },
    "kpis": {
      "lastRun": "2026-04-18T14:05:23Z",
      "status": "updated"
    },
    "timeline": {
      "lastRun": "2026-04-18T14:05:23Z",
      "status": "updated"
    },
    "map-points": {
      "lastRun": "2026-04-18T14:05:23Z",
      "status": "updated"
    },
    "meta": {
      "lastRun": "2026-04-18T14:05:23Z",
      "status": "updated"
    },
    "digests": {
      "lastRun": "2026-04-18T14:05:23Z",
      "status": "updated"
    }
  },
  "consecutiveQuietRuns": 0
}
