{
  "lastRun": "2026-04-21T14:30:00.000Z",
  "tracker": "gaza-war",
  "sections": {
    "events": {
      "lastRun": "2026-04-21T14:30:00.000Z",
      "status": "updated"
    },
    "mapLines": {
      "lastRun": "2026-04-21T14:30:00.000Z",
      "status": "updated"
    },
    "kpis": {
      "lastRun": "2026-04-21T14:30:00.000Z",
      "status": "updated"
    },
    "casualties": {
      "status": "unchanged"
    },
    "political": {
      "status": "unchanged"
    },
    "meta": {
      "lastRun": "2026-04-21T14:30:00.000Z",
      "status": "updated"
    },
    "econ": {
      "lastRun": "2026-04-21T14:30:00.000Z",
      "status": "updated"
    },
    "mapPoints": {
      "status": "unchanged"
    },
    "claims": {
      "status": "unchanged"
    },
    "assets": {
      "status": "unchanged"
    },
    "timeline": {
      "status": "unchanged"
    }
  },
  "consecutiveQuietRuns": 0
}
