{
  "lastRun": "2026-04-22T14:00:37.491Z",
  "tracker": "sudan-conflict",
  "sections": {
    "kpis": {
      "lastRun": "2026-04-22T14:00:37.491Z",
      "status": "updated"
    },
    "timeline": "no-change",
    "mapPoints": "no-change",
    "mapLines": "no-change",
    "casualties": "no-change",
    "econ": "no-change",
    "claims": "no-change",
    "political": {
      "lastRun": "2026-04-22T14:00:37.491Z",
      "status": "updated"
    },
    "assets": "no-change",
    "events": {
      "lastRun": "2026-04-22T14:00:37.491Z",
      "status": "updated"
    },
    "meta": {
      "lastRun": "2026-04-22T14:00:37.491Z",
      "status": "updated"
    },
    "digests": "updated"
  },
  "consecutiveQuietRuns": 0
}
