[
  {
    "id": "rial-34x-divergence-official-market",
    "year": "Dec 22",
    "title": "Official-to-Market Exchange Rate Gap Reaches 34x",
    "type": "economic",
    "detail": "The gap between Iran's official exchange rate of 42,000 rials per dollar and the open market rate of approximately 1,420,000 rials reaches a factor of 34x, the largest divergence in the country's history. The dual-rate system, originally designed to subsidize essential imports, has become a source of massive corruption and arbitrage. Businesses with access to the official rate profit enormously by reselling dollars, while ordinary Iranians and small importers face the full brunt of market rates.",
    "sources": [
      {
        "name": "Eghtesad Online",
        "tier": 2,
        "pole": "middle_eastern"
      },
      {
        "name": "Reuters",
        "tier": 2,
        "pole": "western"
      },
      {
        "name": "NIAC",
        "tier": 3,
        "pole": "western"
      }
    ],
    "media": [
      {
        "type": "image",
        "url": "https://www.iranintl.com/en/202601061682",
        "caption": "Gap between Iran's official and market exchange rates reaches a record 34x divergence",
        "source": "Iran International"
      }
    ],
    "lastUpdated": "2026-03-12"
  },
  {
    "id": "china-demands-deeper-oil-discounts",
    "year": "Dec 22",
    "title": "China Demands Deeper Discounts on Iranian Crude",
    "type": "economic",
    "detail": "Chinese refiners leverage Iran's deepening isolation to demand further price reductions on Iranian crude oil. With most alternative buyers cut off by sanctions enforcement, Iran is forced to accept discounts of $10-15 per barrel below international benchmarks for deliveries to Chinese independent refiners. The discounts, combined with reduced export volumes of approximately 800,000 barrels per day, mean Iran's oil revenue has fallen to a fraction of pre-sanctions levels, further straining the government's ability to fund imports and stabilize the currency.",
    "sources": [
      {
        "name": "Reuters",
        "tier": 2,
        "pole": "western"
      },
      {
        "name": "CGTN",
        "tier": 2,
        "pole": "eastern"
      },
      {
        "name": "CSIS",
        "tier": 3,
        "pole": "western"
      }
    ],
    "media": [
      {
        "type": "image",
        "url": "https://www.iranintl.com/en/202512186544",
        "caption": "Chinese refiners demand deeper discounts on Iranian crude oil, leveraging Tehran's isolation",
        "source": "Iran International",
        "thumbnail": "https://i.iranintl.com/images/rdk9umy0/production/40da2c38638c09190a5adc99c7c2a4552bcb51b3-992x661.png?rect=0,71,992,521&w=1200&h=630&fit=max&auto=format"
      }
    ],
    "lastUpdated": "2026-03-12"
  },
  {
    "id": "internet-throttling-continues",
    "year": "Dec 22",
    "title": "Internet Throttling Persists as Regime Limits Information Flow",
    "type": "humanitarian",
    "detail": "Iran's internet remains throttled to approximately 5% of normal capacity, a restriction imposed during the mid-December crackdown period. The throttling disrupts not only social media and messaging platforms but also e-commerce, online banking, and business communications. Tech companies and startups report massive revenue losses. The regime justifies the restrictions as necessary for national security, but analysts note the pattern of information suppression ahead of anticipated social unrest.",
    "sources": [
      {
        "name": "NetBlocks",
        "tier": 3,
        "pole": "international"
      },
      {
        "name": "ARTICLE 19",
        "tier": 3,
        "pole": "international"
      },
      {
        "name": "Iran International",
        "tier": 2,
        "pole": "middle_eastern"
      }
    ],
    "media": [
      {
        "type": "image",
        "url": "https://cointelegraph.com/features/iran-s-currency-collapse-shows-why-bitcoin-is-seen-as-an-exit-option",
        "caption": "Iran's internet remains throttled to 5% of capacity as regime limits information flow",
        "source": "CoinTelegraph",
        "thumbnail": "https://images.cointelegraph.com/cdn-cgi/image/f=auto,onerror=redirect,w=1200/https://s3.cointelegraph.com/uploads/2026-01/019b93f7-4750-7f9f-a48b-1ee1c2346807.jpg"
      }
    ],
    "lastUpdated": "2026-03-12"
  }
]
