{
  "operationName": "Tlatelolco Massacre",
  "dayCount": 20987,
  "dateline": "19 MAR 2026",
  "heroHeadline": "2 de Outubro de 1968: Exército Abre Fogo Contra Estudantes em Tlatelolco",
  "heroSubtitle": "20.987 dias desde o massacre — o verdadeiro número de mortos (200–400), o destino dos desaparecidos e a responsabilização completa permanecem desconhecidos",
  "footerNote": "Data sourced from declassified CIA/NSA documents, Archivo General de la Nación (AGN), FEMOSPP investigation reports, CNDH, and major outlets including Proceso, La Jornada, and the National Security Archive.",
  "lastUpdated": "2026-03-27T14:52:17Z"
}
