{
  "operationName": "US-LatAm Interventions",
  "dayCount": 46715,
  "dateline": "Latin America — 1898–Present",
  "heroHeadline": "Plus d'un siècle d'interventions américaines : de Cuba au Nicaragua en passant par le Panama",
  "heroSubtitle": "Suivi des coups d'État, des opérations de la CIA, de l'opération Condor et de l'héritage de la doctrine Monroe à travers 18 pays et plus de 125 ans",
  "footerNote": "Data sourced from CIA CREST (declassified), National Security Archive, State Dept FOIA, Church Committee reports, and national truth commissions",
  "lastUpdated": "2026-03-20T00:00:00Z"
}
